[{"ticker":"AAPL","type":"put","expiration":"2015-07-30","strike":"95","contract_name":"AAPL150731P00095000","last":"0.01","bid":"0","ask":"0.01","change":"0","percent_change":"0","volume":"205","open_interest":"205","implied_volatility":"84.38","atm":"1","created_at":"2015-07-28 13:03:05","updated_at":"2015-07-28 13:03:05","moneyness":23.002107310747},{"ticker":"AAPL","type":"put","expiration":"2015-07-30","strike":"100","contract_name":"AAPL150731P00100000","last":"0.01","bid":"0","ask":"0.01","change":"-0.01","percent_change":"-50","volume":"260","open_interest":"480","implied_volatility":"68.75","atm":"1","created_at":"2015-07-28 13:03:05","updated_at":"2015-07-28 13:03:05","moneyness":18.949586642892},{"ticker":"AAPL","type":"put","expiration":"2015-07-30","strike":"105","contract_name":"AAPL150731P00105000","last":"0.01","bid":"0","ask":"0.01","change":"0","percent_change":"0","volume":"2880","open_interest":"5827","implied_volatility":"54.69","atm":"1","created_at":"2015-07-28 13:03:05","updated_at":"2015-07-28 13:03:05","moneyness":14.897065975036},{"ticker":"AAPL","type":"put","expiration":"2015-07-30","strike":"106","contract_name":"AAPL150731P00106000","last":"0.01","bid":"0","ask":"0.01","change":"-0.02","percent_change":"-66.67","volume":"200","open_interest":"4469","implied_volatility":"51.56","atm":"1","created_at":"2015-07-28 13:03:05","updated_at":"2015-07-28 13:03:05","moneyness":14.086561841465},{"ticker":"AAPL","type":"put","expiration":"2015-07-30","strike":"107","contract_name":"AAPL150731P00107000","last":"0.02","bid":"0","ask":"0.01","change":"0","percent_change":"0","volume":"606","open_interest":"852","implied_volatility":"52.34","atm":"1","created_at":"2015-07-28 13:03:05","updated_at":"2015-07-28 13:03:05","moneyness":13.276057707894},{"ticker":"AAPL","type":"put","expiration":"2015-07-30","strike":"108","contract_name":"AAPL150731P00108000","last":"0.02","bid":"0","ask":"0.01","change":"-0.02","percent_change":"-50","volume":"18","open_interest":"1354","implied_volatility":"49.22","atm":"1","created_at":"2015-07-28 13:03:05","updated_at":"2015-07-28 13:03:05","moneyness":12.465553574323},{"ticker":"AAPL","type":"put","expiration":"2015-07-30","strike":"109","contract_name":"AAPL150731P00109000","last":"0.04","bid":"0","ask":"0.02","change":"0","percent_change":"0","volume":"627","open_interest":"645","implied_volatility":"50","atm":"1","created_at":"2015-07-28 13:03:05","updated_at":"2015-07-28 13:03:05","moneyness":11.655049440752},{"ticker":"AAPL","type":"put","expiration":"2015-07-30","strike":"110","contract_name":"AAPL150731P00110000","last":"0.01","bid":"0","ask":"0.02","change":"-0.02","percent_change":"-66.67","volume":"888","open_interest":"4741","implied_volatility":"46.88","atm":"1","created_at":"2015-07-28 13:03:05","updated_at":"2015-07-28 13:03:05","moneyness":10.844545307181},{"ticker":"AAPL","type":"put","expiration":"2015-07-30","strike":"111","contract_name":"AAPL150731P00111000","last":"0.02","bid":"0.01","ask":"0.02","change":"-0.02","percent_change":"-50","volume":"647","open_interest":"3443","implied_volatility":"43.75","atm":"1","created_at":"2015-07-28 13:03:05","updated_at":"2015-07-28 13:03:05","moneyness":10.03404117361},{"ticker":"AAPL","type":"put","expiration":"2015-07-30","strike":"112","contract_name":"AAPL150731P00112000","last":"0.02","bid":"0.01","ask":"0.02","change":"-0.02","percent_change":"-50","volume":"883","open_interest":"2752","implied_volatility":"40.23","atm":"1","created_at":"2015-07-28 13:03:05","updated_at":"2015-07-28 13:03:05","moneyness":9.2235370400389},{"ticker":"AAPL","type":"put","expiration":"2015-07-30","strike":"113","contract_name":"AAPL150731P00113000","last":"0.02","bid":"0.02","ask":"0.03","change":"-0.03","percent_change":"-60","volume":"1681","open_interest":"2498","implied_volatility":"39.06","atm":"1","created_at":"2015-07-28 13:03:05","updated_at":"2015-07-28 13:03:05","moneyness":8.4130329064678},{"ticker":"AAPL","type":"put","expiration":"2015-07-30","strike":"114","contract_name":"AAPL150731P00114000","last":"0.04","bid":"0.02","ask":"0.03","change":"-0.02","percent_change":"-33.33","volume":"70","open_interest":"1825","implied_volatility":"35.55","atm":"1","created_at":"2015-07-28 13:03:05","updated_at":"2015-07-28 13:03:05","moneyness":7.6025287728967},{"ticker":"AAPL","type":"put","expiration":"2015-07-30","strike":"115","contract_name":"AAPL150731P00115000","last":"0.02","bid":"0.02","ask":"0.03","change":"-0.06","percent_change":"-75","volume":"835","open_interest":"9722","implied_volatility":"32.03","atm":"1","created_at":"2015-07-28 13:03:05","updated_at":"2015-07-28 13:03:05","moneyness":6.7920246393257},{"ticker":"AAPL","type":"put","expiration":"2015-07-30","strike":"116","contract_name":"AAPL150731P00116000","last":"0.04","bid":"0.03","ask":"0.04","change":"-0.05","percent_change":"-55.56","volume":"381","open_interest":"5990","implied_volatility":"30.08","atm":"1","created_at":"2015-07-28 13:03:05","updated_at":"2015-07-28 13:03:05","moneyness":5.9815205057546},{"ticker":"AAPL","type":"put","expiration":"2015-07-30","strike":"117","contract_name":"AAPL150731P00117000","last":"0.04","bid":"0.04","ask":"0.05","change":"-0.09","percent_change":"-69.23","volume":"1219","open_interest":"5077","implied_volatility":"27.54","atm":"1","created_at":"2015-07-28 13:03:05","updated_at":"2015-07-28 13:03:05","moneyness":5.1710163721835},{"ticker":"AAPL","type":"put","expiration":"2015-07-30","strike":"118","contract_name":"AAPL150731P00118000","last":"0.06","bid":"0.05","ask":"0.06","change":"-0.12","percent_change":"-66.67","volume":"1664","open_interest":"6979","implied_volatility":"24.61","atm":"1","created_at":"2015-07-28 13:03:05","updated_at":"2015-07-28 13:03:05","moneyness":4.3605122386124},{"ticker":"AAPL","type":"put","expiration":"2015-07-30","strike":"119","contract_name":"AAPL150731P00119000","last":"0.08","bid":"0.08","ask":"0.09","change":"-0.19","percent_change":"-70.37","volume":"2565","open_interest":"9798","implied_volatility":"22.56","atm":"1","created_at":"2015-07-28 13:03:05","updated_at":"2015-07-28 13:03:05","moneyness":3.5500081050413},{"ticker":"AAPL","type":"put","expiration":"2015-07-30","strike":"120","contract_name":"AAPL150731P00120000","last":"0.14","bid":"0.13","ask":"0.14","change":"-0.24","percent_change":"-63.16","volume":"4907","open_interest":"19192","implied_volatility":"20.61","atm":"1","created_at":"2015-07-28 13:03:05","updated_at":"2015-07-28 13:03:05","moneyness":2.7395039714703},{"ticker":"AAPL","type":"put","expiration":"2015-07-30","strike":"121","contract_name":"AAPL150731P00121000","last":"0.24","bid":"0.23","ask":"0.25","change":"-0.39","percent_change":"-61.9","volume":"7768","open_interest":"10496","implied_volatility":"19.29","atm":"1","created_at":"2015-07-28 13:03:05","updated_at":"2015-07-28 13:03:05","moneyness":1.9289998378992},{"ticker":"AAPL","type":"put","expiration":"2015-07-30","strike":"122","contract_name":"AAPL150731P00122000","last":"0.44","bid":"0.43","ask":"0.44","change":"-0.47","percent_change":"-51.65","volume":"18502","open_interest":"13622","implied_volatility":"17.97","atm":"1","created_at":"2015-07-28 13:03:05","updated_at":"2015-07-28 13:03:05","moneyness":1.1184957043281},{"ticker":"AAPL","type":"put","expiration":"2015-07-30","strike":"123","contract_name":"AAPL150731P00123000","last":"0.8","bid":"0.77","ask":"0.79","change":"-0.53","percent_change":"-39.85","volume":"11566","open_interest":"16818","implied_volatility":"17.29","atm":"1","created_at":"2015-07-28 13:03:05","updated_at":"2015-07-28 13:03:05","moneyness":0.30799157075701},{"ticker":"AAPL","type":"put","expiration":"2015-08-06","strike":"100","contract_name":"AAPL150807P00100000","last":"0.04","bid":"0.01","ask":"0.02","change":"0","percent_change":"0","volume":"39","open_interest":"37","implied_volatility":"48.44","atm":"0","created_at":"2015-07-28 13:03:06","updated_at":"2015-07-28 13:03:06","moneyness":18.949586642892},{"ticker":"AAPL","type":"put","expiration":"2015-08-06","strike":"105","contract_name":"AAPL150807P00105000","last":"0.03","bid":"0.03","ask":"0.04","change":"-0.03","percent_change":"-50","volume":"679","open_interest":"26605","implied_volatility":"41.8","atm":"0","created_at":"2015-07-28 13:03:06","updated_at":"2015-07-28 13:03:06","moneyness":14.897065975036},{"ticker":"AAPL","type":"put","expiration":"2015-08-06","strike":"110","contract_name":"AAPL150807P00110000","last":"0.08","bid":"0.06","ask":"0.07","change":"-0.05","percent_change":"-38.46","volume":"258","open_interest":"5640","implied_volatility":"33.79","atm":"0","created_at":"2015-07-28 13:03:06","updated_at":"2015-07-28 13:03:06","moneyness":10.844545307181},{"ticker":"AAPL","type":"put","expiration":"2015-08-06","strike":"113","contract_name":"AAPL150807P00113000","last":"0.1","bid":"0.09","ask":"0.1","change":"-0.1","percent_change":"-50","volume":"190","open_interest":"1400","implied_volatility":"28.81","atm":"0","created_at":"2015-07-28 13:03:06","updated_at":"2015-07-28 13:03:06","moneyness":8.4130329064678},{"ticker":"AAPL","type":"put","expiration":"2015-08-06","strike":"114","contract_name":"AAPL150807P00114000","last":"0.12","bid":"0.11","ask":"0.12","change":"-0.11","percent_change":"-47.83","volume":"418","open_interest":"1961","implied_volatility":"27.34","atm":"0","created_at":"2015-07-28 13:03:06","updated_at":"2015-07-28 13:03:06","moneyness":7.6025287728967},{"ticker":"AAPL","type":"put","expiration":"2015-08-06","strike":"115","contract_name":"AAPL150807P00115000","last":"0.14","bid":"0.13","ask":"0.14","change":"-0.14","percent_change":"-50","volume":"491","open_interest":"2682","implied_volatility":"25.68","atm":"0","created_at":"2015-07-28 13:03:06","updated_at":"2015-07-28 13:03:06","moneyness":6.7920246393257},{"ticker":"AAPL","type":"put","expiration":"2015-08-06","strike":"116","contract_name":"AAPL150807P00116000","last":"0.17","bid":"0.17","ask":"0.17","change":"-0.19","percent_change":"-52.78","volume":"171","open_interest":"2177","implied_volatility":"24.17","atm":"0","created_at":"2015-07-28 13:03:06","updated_at":"2015-07-28 13:03:06","moneyness":5.9815205057546},{"ticker":"AAPL","type":"put","expiration":"2015-08-06","strike":"117","contract_name":"AAPL150807P00117000","last":"0.23","bid":"0.22","ask":"0.23","change":"-0.23","percent_change":"-50","volume":"519","open_interest":"1655","implied_volatility":"23.24","atm":"0","created_at":"2015-07-28 13:03:06","updated_at":"2015-07-28 13:03:06","moneyness":5.1710163721835},{"ticker":"AAPL","type":"put","expiration":"2015-08-06","strike":"118","contract_name":"AAPL150807P00118000","last":"0.31","bid":"0.3","ask":"0.32","change":"-0.29","percent_change":"-48.33","volume":"411","open_interest":"2450","implied_volatility":"22.51","atm":"0","created_at":"2015-07-28 13:03:06","updated_at":"2015-07-28 13:03:06","moneyness":4.3605122386124},{"ticker":"AAPL","type":"put","expiration":"2015-08-06","strike":"119","contract_name":"AAPL150807P00119000","last":"0.41","bid":"0.42","ask":"0.44","change":"-0.39","percent_change":"-48.75","volume":"800","open_interest":"3520","implied_volatility":"21.7","atm":"0","created_at":"2015-07-28 13:03:06","updated_at":"2015-07-28 13:03:06","moneyness":3.5500081050413},{"ticker":"AAPL","type":"put","expiration":"2015-08-06","strike":"120","contract_name":"AAPL150807P00120000","last":"0.63","bid":"0.63","ask":"0.64","change":"-0.49","percent_change":"-43.75","volume":"1550","open_interest":"4053","implied_volatility":"21.49","atm":"0","created_at":"2015-07-28 13:03:06","updated_at":"2015-07-28 13:03:06","moneyness":2.7395039714703},{"ticker":"AAPL","type":"put","expiration":"2015-08-06","strike":"121","contract_name":"AAPL150807P00121000","last":"0.88","bid":"0.87","ask":"0.88","change":"-0.55","percent_change":"-38.46","volume":"1439","open_interest":"6676","implied_volatility":"20.9","atm":"0","created_at":"2015-07-28 13:03:06","updated_at":"2015-07-28 13:03:06","moneyness":1.9289998378992},{"ticker":"AAPL","type":"put","expiration":"2015-08-06","strike":"122","contract_name":"AAPL150807P00122000","last":"1.25","bid":"1.22","ask":"1.24","change":"-0.59","percent_change":"-32.07","volume":"1538","open_interest":"7461","implied_volatility":"20.95","atm":"0","created_at":"2015-07-28 13:03:06","updated_at":"2015-07-28 13:03:06","moneyness":1.1184957043281},{"ticker":"AAPL","type":"put","expiration":"2015-08-06","strike":"123","contract_name":"AAPL150807P00123000","last":"1.68","bid":"1.67","ask":"1.68","change":"-0.66","percent_change":"-28.21","volume":"797","open_interest":"0","implied_volatility":"20.9","atm":"0","created_at":"2015-07-28 13:03:06","updated_at":"2015-07-28 13:03:06","moneyness":0.30799157075701},{"ticker":"AAPL","type":"put","expiration":"2015-08-13","strike":"105","contract_name":"AAPL150814P00105000","last":"0.07","bid":"0.07","ask":"0.09","change":"-0.05","percent_change":"-41.67","volume":"201","open_interest":"1353","implied_volatility":"36.91","atm":"0","created_at":"2015-07-28 13:03:06","updated_at":"2015-07-28 13:03:06","moneyness":14.897065975036},{"ticker":"AAPL","type":"put","expiration":"2015-08-13","strike":"110","contract_name":"AAPL150814P00110000","last":"0.15","bid":"0.12","ask":"0.13","change":"-0.06","percent_change":"-28.57","volume":"6","open_interest":"2477","implied_volatility":"29.49","atm":"0","created_at":"2015-07-28 13:03:06","updated_at":"2015-07-28 13:03:06","moneyness":10.844545307181},{"ticker":"AAPL","type":"put","expiration":"2015-08-13","strike":"112","contract_name":"AAPL150814P00112000","last":"0.22","bid":"0.16","ask":"0.17","change":"-0.07","percent_change":"-24.14","volume":"1","open_interest":"283","implied_volatility":"27.05","atm":"0","created_at":"2015-07-28 13:03:06","updated_at":"2015-07-28 13:03:06","moneyness":9.2235370400389},{"ticker":"AAPL","type":"put","expiration":"2015-08-13","strike":"113","contract_name":"AAPL150814P00113000","last":"0.29","bid":"0.18","ask":"0.19","change":"-0.03","percent_change":"-9.38","volume":"5","open_interest":"465","implied_volatility":"25.68","atm":"0","created_at":"2015-07-28 13:03:06","updated_at":"2015-07-28 13:03:06","moneyness":8.4130329064678},{"ticker":"AAPL","type":"put","expiration":"2015-08-13","strike":"114","contract_name":"AAPL150814P00114000","last":"0.35","bid":"0.23","ask":"0.24","change":"-0.02","percent_change":"-5.41","volume":"49","open_interest":"679","implied_volatility":"24.95","atm":"0","created_at":"2015-07-28 13:03:06","updated_at":"2015-07-28 13:03:06","moneyness":7.6025287728967},{"ticker":"AAPL","type":"put","expiration":"2015-08-13","strike":"115","contract_name":"AAPL150814P00115000","last":"0.27","bid":"0.28","ask":"0.29","change":"-0.25","percent_change":"-48.08","volume":"25","open_interest":"3002","implied_volatility":"23.93","atm":"0","created_at":"2015-07-28 13:03:06","updated_at":"2015-07-28 13:03:06","moneyness":6.7920246393257},{"ticker":"AAPL","type":"put","expiration":"2015-08-13","strike":"116","contract_name":"AAPL150814P00116000","last":"0.4","bid":"0.36","ask":"0.37","change":"-0.25","percent_change":"-38.46","volume":"58","open_interest":"963","implied_volatility":"23.24","atm":"0","created_at":"2015-07-28 13:03:06","updated_at":"2015-07-28 13:03:06","moneyness":5.9815205057546},{"ticker":"AAPL","type":"put","expiration":"2015-08-13","strike":"117","contract_name":"AAPL150814P00117000","last":"0.67","bid":"0.46","ask":"0.47","change":"-0.16","percent_change":"-19.28","volume":"43","open_interest":"638","implied_volatility":"22.51","atm":"0","created_at":"2015-07-28 13:03:06","updated_at":"2015-07-28 13:03:06","moneyness":5.1710163721835},{"ticker":"AAPL","type":"put","expiration":"2015-08-13","strike":"118","contract_name":"AAPL150814P00118000","last":"0.64","bid":"0.6","ask":"0.61","change":"-0.39","percent_change":"-37.86","volume":"163","open_interest":"2045","implied_volatility":"21.97","atm":"0","created_at":"2015-07-28 13:03:06","updated_at":"2015-07-28 13:03:06","moneyness":4.3605122386124},{"ticker":"AAPL","type":"put","expiration":"2015-08-13","strike":"119","contract_name":"AAPL150814P00119000","last":"0.75","bid":"0.79","ask":"0.8","change":"-0.52","percent_change":"-40.94","volume":"354","open_interest":"2007","implied_volatility":"21.61","atm":"0","created_at":"2015-07-28 13:03:06","updated_at":"2015-07-28 13:03:06","moneyness":3.5500081050413},{"ticker":"AAPL","type":"put","expiration":"2015-08-13","strike":"120","contract_name":"AAPL150814P00120000","last":"1","bid":"1.02","ask":"1.04","change":"-0.53","percent_change":"-34.64","volume":"1107","open_interest":"3058","implied_volatility":"21.29","atm":"0","created_at":"2015-07-28 13:03:06","updated_at":"2015-07-28 13:03:06","moneyness":2.7395039714703},{"ticker":"AAPL","type":"put","expiration":"2015-08-13","strike":"121","contract_name":"AAPL150814P00121000","last":"1.31","bid":"1.33","ask":"1.35","change":"-0.58","percent_change":"-30.69","volume":"211","open_interest":"2535","implied_volatility":"21.09","atm":"0","created_at":"2015-07-28 13:03:06","updated_at":"2015-07-28 13:03:06","moneyness":1.9289998378992},{"ticker":"AAPL","type":"put","expiration":"2015-08-13","strike":"122","contract_name":"AAPL150814P00122000","last":"1.76","bid":"1.72","ask":"1.73","change":"-0.55","percent_change":"-23.81","volume":"407","open_interest":"4435","implied_volatility":"20.97","atm":"0","created_at":"2015-07-28 13:03:06","updated_at":"2015-07-28 13:03:06","moneyness":1.1184957043281},{"ticker":"AAPL","type":"put","expiration":"2015-08-13","strike":"123","contract_name":"AAPL150814P00123000","last":"2.13","bid":"2.18","ask":"2.19","change":"-0.7","percent_change":"-24.73","volume":"340","open_interest":"3403","implied_volatility":"20.97","atm":"0","created_at":"2015-07-28 13:03:06","updated_at":"2015-07-28 13:03:06","moneyness":0.30799157075701},{"ticker":"AAPL","type":"put","expiration":"2015-08-20","strike":"65","contract_name":"AAPL150821P00065000","last":"0.02","bid":"0","ask":"0.01","change":"0","percent_change":"0","volume":"0","open_interest":"13","implied_volatility":"78.13","atm":"0","created_at":"2015-07-28 13:03:06","updated_at":"2015-07-28 13:03:06","moneyness":47.31723131788},{"ticker":"AAPL","type":"put","expiration":"2015-08-20","strike":"70","contract_name":"AAPL150821P00070000","last":"0.01","bid":"0","ask":"0.01","change":"0","percent_change":"0","volume":"0","open_interest":"1491","implied_volatility":"70.31","atm":"0","created_at":"2015-07-28 13:03:06","updated_at":"2015-07-28 13:03:06","moneyness":43.264710650024},{"ticker":"AAPL","type":"put","expiration":"2015-08-20","strike":"75","contract_name":"AAPL150821P00075000","last":"0.01","bid":"0","ask":"0.01","change":"0","percent_change":"0","volume":"0","open_interest":"15180","implied_volatility":"62.5","atm":"0","created_at":"2015-07-28 13:03:06","updated_at":"2015-07-28 13:03:06","moneyness":39.212189982169},{"ticker":"AAPL","type":"put","expiration":"2015-08-20","strike":"80","contract_name":"AAPL150821P00080000","last":"0.01","bid":"0","ask":"0.01","change":"0","percent_change":"0","volume":"0","open_interest":"16944","implied_volatility":"54.69","atm":"0","created_at":"2015-07-28 13:03:06","updated_at":"2015-07-28 13:03:06","moneyness":35.159669314314},{"ticker":"AAPL","type":"put","expiration":"2015-08-20","strike":"85","contract_name":"AAPL150821P00085000","last":"0.03","bid":"0.01","ask":"0.02","change":"0","percent_change":"0","volume":"46","open_interest":"21249","implied_volatility":"52.34","atm":"0","created_at":"2015-07-28 13:03:06","updated_at":"2015-07-28 13:03:06","moneyness":31.107148646458},{"ticker":"AAPL","type":"put","expiration":"2015-08-20","strike":"87.5","contract_name":"AAPL150821P00087500","last":"0.04","bid":"0.02","ask":"0.03","change":"0","percent_change":"0","volume":"5","open_interest":"272","implied_volatility":"51.56","atm":"0","created_at":"2015-07-28 13:03:06","updated_at":"2015-07-28 13:03:06","moneyness":29.08088831253},{"ticker":"AAPL","type":"put","expiration":"2015-08-20","strike":"90","contract_name":"AAPL150821P00090000","last":"0.03","bid":"0.03","ask":"0.04","change":"-0.02","percent_change":"-40","volume":"1030","open_interest":"13697","implied_volatility":"50.39","atm":"0","created_at":"2015-07-28 13:03:06","updated_at":"2015-07-28 13:03:06","moneyness":27.054627978603},{"ticker":"AAPL","type":"put","expiration":"2015-08-20","strike":"92.5","contract_name":"AAPL150821P00092500","last":"0.06","bid":"0.04","ask":"0.05","change":"0","percent_change":"0","volume":"12","open_interest":"112","implied_volatility":"47.66","atm":"0","created_at":"2015-07-28 13:03:06","updated_at":"2015-07-28 13:03:06","moneyness":25.028367644675},{"ticker":"AAPL","type":"put","expiration":"2015-08-20","strike":"95","contract_name":"AAPL150821P00095000","last":"0.05","bid":"0.05","ask":"0.06","change":"-0.03","percent_change":"-37.5","volume":"120","open_interest":"5683","implied_volatility":"44.92","atm":"0","created_at":"2015-07-28 13:03:06","updated_at":"2015-07-28 13:03:06","moneyness":23.002107310747},{"ticker":"AAPL","type":"put","expiration":"2015-08-20","strike":"97.5","contract_name":"AAPL150821P00097500","last":"0.09","bid":"0.06","ask":"0.07","change":"0","percent_change":"0","volume":"11","open_interest":"574","implied_volatility":"41.8","atm":"0","created_at":"2015-07-28 13:03:06","updated_at":"2015-07-28 13:03:06","moneyness":20.97584697682},{"ticker":"AAPL","type":"put","expiration":"2015-08-20","strike":"100","contract_name":"AAPL150821P00100000","last":"0.08","bid":"0.08","ask":"0.09","change":"-0.03","percent_change":"-27.27","volume":"335","open_interest":"25214","implied_volatility":"39.26","atm":"0","created_at":"2015-07-28 13:03:06","updated_at":"2015-07-28 13:03:06","moneyness":18.949586642892},{"ticker":"AAPL","type":"put","expiration":"2015-08-20","strike":"105","contract_name":"AAPL150821P00105000","last":"0.13","bid":"0.12","ask":"0.13","change":"-0.06","percent_change":"-31.58","volume":"52","open_interest":"25518","implied_volatility":"33.3","atm":"0","created_at":"2015-07-28 13:03:06","updated_at":"2015-07-28 13:03:06","moneyness":14.897065975036},{"ticker":"AAPL","type":"put","expiration":"2015-08-20","strike":"106","contract_name":"AAPL150821P00106000","last":"0.2","bid":"0.13","ask":"0.14","change":"0","percent_change":"0","volume":"22","open_interest":"645","implied_volatility":"32.08","atm":"0","created_at":"2015-07-28 13:03:06","updated_at":"2015-07-28 13:03:06","moneyness":14.086561841465},{"ticker":"AAPL","type":"put","expiration":"2015-08-20","strike":"107","contract_name":"AAPL150821P00107000","last":"0.18","bid":"0.14","ask":"0.15","change":"-0.05","percent_change":"-21.74","volume":"5","open_interest":"1002","implied_volatility":"30.76","atm":"0","created_at":"2015-07-28 13:03:06","updated_at":"2015-07-28 13:03:06","moneyness":13.276057707894},{"ticker":"AAPL","type":"put","expiration":"2015-08-20","strike":"108","contract_name":"AAPL150821P00108000","last":"0.2","bid":"0.16","ask":"0.17","change":"-0.06","percent_change":"-23.08","volume":"15","open_interest":"752","implied_volatility":"29.83","atm":"0","created_at":"2015-07-28 13:03:06","updated_at":"2015-07-28 13:03:06","moneyness":12.465553574323},{"ticker":"AAPL","type":"put","expiration":"2015-08-20","strike":"109","contract_name":"AAPL150821P00109000","last":"0.2","bid":"0.17","ask":"0.18","change":"-0.09","percent_change":"-31.03","volume":"57","open_interest":"1028","implied_volatility":"28.42","atm":"0","created_at":"2015-07-28 13:03:06","updated_at":"2015-07-28 13:03:06","moneyness":11.655049440752},{"ticker":"AAPL","type":"put","expiration":"2015-08-20","strike":"110","contract_name":"AAPL150821P00110000","last":"0.21","bid":"0.2","ask":"0.21","change":"-0.12","percent_change":"-36.36","volume":"527","open_interest":"33384","implied_volatility":"27.59","atm":"0","created_at":"2015-07-28 13:03:06","updated_at":"2015-07-28 13:03:06","moneyness":10.844545307181},{"ticker":"AAPL","type":"put","expiration":"2015-08-20","strike":"111","contract_name":"AAPL150821P00111000","last":"0.25","bid":"0.23","ask":"0.24","change":"-0.12","percent_change":"-32.43","volume":"121","open_interest":"1892","implied_volatility":"26.61","atm":"0","created_at":"2015-07-28 13:03:06","updated_at":"2015-07-28 13:03:06","moneyness":10.03404117361},{"ticker":"AAPL","type":"put","expiration":"2015-08-20","strike":"112","contract_name":"AAPL150821P00112000","last":"0.27","bid":"0.27","ask":"0.28","change":"-0.17","percent_change":"-38.64","volume":"62","open_interest":"1993","implied_volatility":"25.73","atm":"0","created_at":"2015-07-28 13:03:06","updated_at":"2015-07-28 13:03:06","moneyness":9.2235370400389},{"ticker":"AAPL","type":"put","expiration":"2015-08-20","strike":"113","contract_name":"AAPL150821P00113000","last":"0.39","bid":"0.32","ask":"0.33","change":"-0.11","percent_change":"-22","volume":"40","open_interest":"1802","implied_volatility":"24.88","atm":"0","created_at":"2015-07-28 13:03:06","updated_at":"2015-07-28 13:03:06","moneyness":8.4130329064678},{"ticker":"AAPL","type":"put","expiration":"2015-08-20","strike":"114","contract_name":"AAPL150821P00114000","last":"0.55","bid":"0.38","ask":"0.39","change":"-0.06","percent_change":"-9.84","volume":"65","open_interest":"1727","implied_volatility":"24.02","atm":"0","created_at":"2015-07-28 13:03:06","updated_at":"2015-07-28 13:03:06","moneyness":7.6025287728967},{"ticker":"AAPL","type":"put","expiration":"2015-08-20","strike":"115","contract_name":"AAPL150821P00115000","last":"0.48","bid":"0.47","ask":"0.49","change":"-0.24","percent_change":"-33.33","volume":"2034","open_interest":"56778","implied_volatility":"23.61","atm":"0","created_at":"2015-07-28 13:03:06","updated_at":"2015-07-28 13:03:06","moneyness":6.7920246393257},{"ticker":"AAPL","type":"put","expiration":"2015-08-20","strike":"116","contract_name":"AAPL150821P00116000","last":"0.61","bid":"0.57","ask":"0.59","change":"-0.28","percent_change":"-31.46","volume":"69","open_interest":"4176","implied_volatility":"22.88","atm":"0","created_at":"2015-07-28 13:03:06","updated_at":"2015-07-28 13:03:06","moneyness":5.9815205057546},{"ticker":"AAPL","type":"put","expiration":"2015-08-20","strike":"117","contract_name":"AAPL150821P00117000","last":"0.7","bid":"0.71","ask":"0.73","change":"-0.37","percent_change":"-34.58","volume":"429","open_interest":"4509","implied_volatility":"22.36","atm":"0","created_at":"2015-07-28 13:03:06","updated_at":"2015-07-28 13:03:06","moneyness":5.1710163721835},{"ticker":"AAPL","type":"put","expiration":"2015-08-20","strike":"118","contract_name":"AAPL150821P00118000","last":"0.93","bid":"0.89","ask":"0.9","change":"-0.37","percent_change":"-28.46","volume":"859","open_interest":"6297","implied_volatility":"21.88","atm":"0","created_at":"2015-07-28 13:03:06","updated_at":"2015-07-28 13:03:06","moneyness":4.3605122386124},{"ticker":"AAPL","type":"put","expiration":"2015-08-20","strike":"119","contract_name":"AAPL150821P00119000","last":"1.14","bid":"1.12","ask":"1.14","change":"-0.44","percent_change":"-27.85","volume":"625","open_interest":"5512","implied_volatility":"21.7","atm":"0","created_at":"2015-07-28 13:03:06","updated_at":"2015-07-28 13:03:06","moneyness":3.5500081050413},{"ticker":"AAPL","type":"put","expiration":"2015-08-20","strike":"120","contract_name":"AAPL150821P00120000","last":"1.4","bid":"1.4","ask":"1.41","change":"-0.49","percent_change":"-25.93","volume":"5114","open_interest":"59965","implied_volatility":"21.39","atm":"0","created_at":"2015-07-28 13:03:06","updated_at":"2015-07-28 13:03:06","moneyness":2.7395039714703},{"ticker":"AAPL","type":"put","expiration":"2015-08-20","strike":"121","contract_name":"AAPL150821P00121000","last":"1.77","bid":"1.74","ask":"1.75","change":"-0.51","percent_change":"-22.37","volume":"2683","open_interest":"3929","implied_volatility":"21.24","atm":"0","created_at":"2015-07-28 13:03:06","updated_at":"2015-07-28 13:03:06","moneyness":1.9289998378992},{"ticker":"AAPL","type":"put","expiration":"2015-08-20","strike":"122","contract_name":"AAPL150821P00122000","last":"2.05","bid":"2.13","ask":"2.15","change":"-0.67","percent_change":"-24.63","volume":"1350","open_interest":"5132","implied_volatility":"21.14","atm":"0","created_at":"2015-07-28 13:03:06","updated_at":"2015-07-28 13:03:06","moneyness":1.1184957043281},{"ticker":"AAPL","type":"put","expiration":"2015-08-20","strike":"123","contract_name":"AAPL150821P00123000","last":"2.65","bid":"2.63","ask":"2.65","change":"-0.6","percent_change":"-18.46","volume":"1074","open_interest":"10760","implied_volatility":"21.38","atm":"0","created_at":"2015-07-28 13:03:06","updated_at":"2015-07-28 13:03:06","moneyness":0.30799157075701},{"ticker":"AAPL","type":"put","expiration":"2015-08-27","strike":"95","contract_name":"AAPL150828P00095000","last":"0.08","bid":"0.06","ask":"0.09","change":"0","percent_change":"0","volume":"24","open_interest":"47","implied_volatility":"41.99","atm":"0","created_at":"2015-07-28 13:03:07","updated_at":"2015-07-28 13:03:07","moneyness":23.002107310747},{"ticker":"AAPL","type":"put","expiration":"2015-08-27","strike":"100","contract_name":"AAPL150828P00100000","last":"0.14","bid":"0.1","ask":"0.13","change":"0","percent_change":"0","volume":"331","open_interest":"623","implied_volatility":"36.91","atm":"0","created_at":"2015-07-28 13:03:07","updated_at":"2015-07-28 13:03:07","moneyness":18.949586642892},{"ticker":"AAPL","type":"put","expiration":"2015-08-27","strike":"105","contract_name":"AAPL150828P00105000","last":"0.24","bid":"0.15","ask":"0.17","change":"0","percent_change":"0","volume":"39","open_interest":"643","implied_volatility":"30.96","atm":"0","created_at":"2015-07-28 13:03:07","updated_at":"2015-07-28 13:03:07","moneyness":14.897065975036},{"ticker":"AAPL","type":"put","expiration":"2015-08-27","strike":"109","contract_name":"AAPL150828P00109000","last":"0.37","bid":"0.24","ask":"0.25","change":"0","percent_change":"0","volume":"382","open_interest":"665","implied_volatility":"26.95","atm":"0","created_at":"2015-07-28 13:03:07","updated_at":"2015-07-28 13:03:07","moneyness":11.655049440752},{"ticker":"AAPL","type":"put","expiration":"2015-08-27","strike":"110","contract_name":"AAPL150828P00110000","last":"0.38","bid":"0.27","ask":"0.29","change":"-0.03","percent_change":"-7.32","volume":"100","open_interest":"451","implied_volatility":"26.22","atm":"0","created_at":"2015-07-28 13:03:07","updated_at":"2015-07-28 13:03:07","moneyness":10.844545307181},{"ticker":"AAPL","type":"put","expiration":"2015-08-27","strike":"111","contract_name":"AAPL150828P00111000","last":"0.47","bid":"0.32","ask":"0.34","change":"0","percent_change":"0","volume":"32","open_interest":"197","implied_volatility":"25.56","atm":"0","created_at":"2015-07-28 13:03:07","updated_at":"2015-07-28 13:03:07","moneyness":10.03404117361},{"ticker":"AAPL","type":"put","expiration":"2015-08-27","strike":"112","contract_name":"AAPL150828P00112000","last":"0.54","bid":"0.37","ask":"0.39","change":"-0.01","percent_change":"-1.82","volume":"3","open_interest":"479","implied_volatility":"24.73","atm":"0","created_at":"2015-07-28 13:03:07","updated_at":"2015-07-28 13:03:07","moneyness":9.2235370400389},{"ticker":"AAPL","type":"put","expiration":"2015-08-27","strike":"113","contract_name":"AAPL150828P00113000","last":"0.6","bid":"0.45","ask":"0.47","change":"-0.03","percent_change":"-4.76","volume":"21","open_interest":"522","implied_volatility":"24.24","atm":"0","created_at":"2015-07-28 13:03:07","updated_at":"2015-07-28 13:03:07","moneyness":8.4130329064678},{"ticker":"AAPL","type":"put","expiration":"2015-08-27","strike":"114","contract_name":"AAPL150828P00114000","last":"0.58","bid":"0.53","ask":"0.56","change":"-0.22","percent_change":"-27.5","volume":"18","open_interest":"382","implied_volatility":"23.66","atm":"0","created_at":"2015-07-28 13:03:07","updated_at":"2015-07-28 13:03:07","moneyness":7.6025287728967},{"ticker":"AAPL","type":"put","expiration":"2015-08-27","strike":"115","contract_name":"AAPL150828P00115000","last":"0.66","bid":"0.65","ask":"0.68","change":"-0.27","percent_change":"-29.03","volume":"488","open_interest":"3960","implied_volatility":"23.24","atm":"0","created_at":"2015-07-28 13:03:07","updated_at":"2015-07-28 13:03:07","moneyness":6.7920246393257},{"ticker":"AAPL","type":"put","expiration":"2015-08-27","strike":"116","contract_name":"AAPL150828P00116000","last":"1.02","bid":"0.79","ask":"0.82","change":"-0.05","percent_change":"-4.67","volume":"108","open_interest":"907","implied_volatility":"22.78","atm":"0","created_at":"2015-07-28 13:03:07","updated_at":"2015-07-28 13:03:07","moneyness":5.9815205057546},{"ticker":"AAPL","type":"put","expiration":"2015-08-27","strike":"117","contract_name":"AAPL150828P00117000","last":"0.98","bid":"0.96","ask":"0.99","change":"-0.43","percent_change":"-30.5","volume":"75","open_interest":"3050","implied_volatility":"22.38","atm":"0","created_at":"2015-07-28 13:03:07","updated_at":"2015-07-28 13:03:07","moneyness":5.1710163721835},{"ticker":"AAPL","type":"put","expiration":"2015-08-27","strike":"118","contract_name":"AAPL150828P00118000","last":"1.2","bid":"1.19","ask":"1.21","change":"-0.44","percent_change":"-26.83","volume":"260","open_interest":"3318","implied_volatility":"22.14","atm":"0","created_at":"2015-07-28 13:03:07","updated_at":"2015-07-28 13:03:07","moneyness":4.3605122386124},{"ticker":"AAPL","type":"put","expiration":"2015-08-27","strike":"119","contract_name":"AAPL150828P00119000","last":"1.47","bid":"1.42","ask":"1.47","change":"-0.45","percent_change":"-23.44","volume":"120","open_interest":"3484","implied_volatility":"21.91","atm":"0","created_at":"2015-07-28 13:03:07","updated_at":"2015-07-28 13:03:07","moneyness":3.5500081050413},{"ticker":"AAPL","type":"put","expiration":"2015-08-27","strike":"120","contract_name":"AAPL150828P00120000","last":"1.76","bid":"1.73","ask":"1.77","change":"-0.49","percent_change":"-21.78","volume":"268","open_interest":"4997","implied_volatility":"21.68","atm":"0","created_at":"2015-07-28 13:03:07","updated_at":"2015-07-28 13:03:07","moneyness":2.7395039714703},{"ticker":"AAPL","type":"put","expiration":"2015-08-27","strike":"121","contract_name":"AAPL150828P00121000","last":"2.5","bid":"2.09","ask":"2.13","change":"-0.18","percent_change":"-6.72","volume":"100","open_interest":"1228","implied_volatility":"21.56","atm":"0","created_at":"2015-07-28 13:03:07","updated_at":"2015-07-28 13:03:07","moneyness":1.9289998378992},{"ticker":"AAPL","type":"put","expiration":"2015-08-27","strike":"122","contract_name":"AAPL150828P00122000","last":"2.5","bid":"2.49","ask":"2.55","change":"-0.65","percent_change":"-20.63","volume":"225","open_interest":"788","implied_volatility":"21.52","atm":"0","created_at":"2015-07-28 13:03:07","updated_at":"2015-07-28 13:03:07","moneyness":1.1184957043281},{"ticker":"AAPL","type":"put","expiration":"2015-08-27","strike":"123","contract_name":"AAPL150828P00123000","last":"3.02","bid":"2.96","ask":"3.05","change":"-0.62","percent_change":"-17.03","volume":"163","open_interest":"739","implied_volatility":"21.68","atm":"0","created_at":"2015-07-28 13:03:07","updated_at":"2015-07-28 13:03:07","moneyness":0.30799157075701},{"ticker":"AAPL","type":"put","expiration":"2015-09-03","strike":"110","contract_name":"AAPL150904P00110000","last":"0.5","bid":"0.36","ask":"0.4","change":"-0.02","percent_change":"-3.85","volume":"30","open_interest":"164","implied_volatility":"25.68","atm":"0","created_at":"2015-07-28 13:03:07","updated_at":"2015-07-28 13:03:07","moneyness":10.844545307181},{"ticker":"AAPL","type":"put","expiration":"2015-09-03","strike":"111","contract_name":"AAPL150904P00111000","last":"0.45","bid":"0.42","ask":"0.46","change":"0","percent_change":"0","volume":"87","open_interest":"117","implied_volatility":"25.05","atm":"0","created_at":"2015-07-28 13:03:07","updated_at":"2015-07-28 13:03:07","moneyness":10.03404117361},{"ticker":"AAPL","type":"put","expiration":"2015-09-03","strike":"112","contract_name":"AAPL150904P00112000","last":"0.74","bid":"0.49","ask":"0.54","change":"0","percent_change":"0","volume":"63","open_interest":"91","implied_volatility":"24.54","atm":"0","created_at":"2015-07-28 13:03:07","updated_at":"2015-07-28 13:03:07","moneyness":9.2235370400389},{"ticker":"AAPL","type":"put","expiration":"2015-09-03","strike":"113","contract_name":"AAPL150904P00113000","last":"0.64","bid":"0.59","ask":"0.63","change":"-0.23","percent_change":"-26.44","volume":"3","open_interest":"32","implied_volatility":"23.98","atm":"0","created_at":"2015-07-28 13:03:07","updated_at":"2015-07-28 13:03:07","moneyness":8.4130329064678},{"ticker":"AAPL","type":"put","expiration":"2015-09-03","strike":"114","contract_name":"AAPL150904P00114000","last":"0.74","bid":"0.7","ask":"0.75","change":"-0.26","percent_change":"-26","volume":"14","open_interest":"182","implied_volatility":"23.58","atm":"0","created_at":"2015-07-28 13:03:07","updated_at":"2015-07-28 13:03:07","moneyness":7.6025287728967},{"ticker":"AAPL","type":"put","expiration":"2015-09-03","strike":"115","contract_name":"AAPL150904P00115000","last":"0.85","bid":"0.84","ask":"0.88","change":"-0.33","percent_change":"-27.97","volume":"173","open_interest":"148","implied_volatility":"23.1","atm":"0","created_at":"2015-07-28 13:03:07","updated_at":"2015-07-28 13:03:07","moneyness":6.7920246393257},{"ticker":"AAPL","type":"put","expiration":"2015-09-03","strike":"116","contract_name":"AAPL150904P00116000","last":"1.08","bid":"1","ask":"1.05","change":"-0.31","percent_change":"-22.3","volume":"209","open_interest":"541","implied_volatility":"22.75","atm":"0","created_at":"2015-07-28 13:03:07","updated_at":"2015-07-28 13:03:07","moneyness":5.9815205057546},{"ticker":"AAPL","type":"put","expiration":"2015-09-03","strike":"117","contract_name":"AAPL150904P00117000","last":"1.51","bid":"1.2","ask":"1.25","change":"-0.08","percent_change":"-5.03","volume":"30","open_interest":"527","implied_volatility":"22.46","atm":"0","created_at":"2015-07-28 13:03:07","updated_at":"2015-07-28 13:03:07","moneyness":5.1710163721835},{"ticker":"AAPL","type":"put","expiration":"2015-09-03","strike":"118","contract_name":"AAPL150904P00118000","last":"1.43","bid":"1.44","ask":"1.49","change":"-0.53","percent_change":"-27.04","volume":"94","open_interest":"491","implied_volatility":"22.22","atm":"0","created_at":"2015-07-28 13:03:07","updated_at":"2015-07-28 13:03:07","moneyness":4.3605122386124},{"ticker":"AAPL","type":"put","expiration":"2015-09-03","strike":"119","contract_name":"AAPL150904P00119000","last":"1.81","bid":"1.72","ask":"1.77","change":"-0.46","percent_change":"-20.26","volume":"11","open_interest":"510","implied_volatility":"22.02","atm":"0","created_at":"2015-07-28 13:03:07","updated_at":"2015-07-28 13:03:07","moneyness":3.5500081050413},{"ticker":"AAPL","type":"put","expiration":"2015-09-03","strike":"120","contract_name":"AAPL150904P00120000","last":"2.07","bid":"2.04","ask":"2.1","change":"-0.49","percent_change":"-19.14","volume":"35","open_interest":"194","implied_volatility":"21.89","atm":"0","created_at":"2015-07-28 13:03:07","updated_at":"2015-07-28 13:03:07","moneyness":2.7395039714703},{"ticker":"AAPL","type":"put","expiration":"2015-09-03","strike":"121","contract_name":"AAPL150904P00121000","last":"2.39","bid":"2.41","ask":"2.47","change":"-0.6","percent_change":"-20.07","volume":"44","open_interest":"37","implied_volatility":"21.74","atm":"0","created_at":"2015-07-28 13:03:07","updated_at":"2015-07-28 13:03:07","moneyness":1.9289998378992},{"ticker":"AAPL","type":"put","expiration":"2015-09-03","strike":"122","contract_name":"AAPL150904P00122000","last":"2.91","bid":"2.82","ask":"2.88","change":"-0.55","percent_change":"-15.9","volume":"139","open_interest":"90","implied_volatility":"21.58","atm":"0","created_at":"2015-07-28 13:03:07","updated_at":"2015-07-28 13:03:07","moneyness":1.1184957043281},{"ticker":"AAPL","type":"put","expiration":"2015-09-03","strike":"123","contract_name":"AAPL150904P00123000","last":"3.85","bid":"3.3","ask":"3.4","change":"-0.11","percent_change":"-2.78","volume":"28","open_interest":"93","implied_volatility":"21.83","atm":"0","created_at":"2015-07-28 13:03:07","updated_at":"2015-07-28 13:03:07","moneyness":0.30799157075701},{"ticker":"AAPL","type":"put","expiration":"2015-09-17","strike":"65","contract_name":"AAPL150918P00065000","last":"0.02","bid":"0","ask":"0.02","change":"0","percent_change":"0","volume":"110","open_interest":"155","implied_volatility":"57.81","atm":"0","created_at":"2015-07-28 13:03:07","updated_at":"2015-07-28 13:03:07","moneyness":47.31723131788},{"ticker":"AAPL","type":"put","expiration":"2015-09-17","strike":"70","contract_name":"AAPL150918P00070000","last":"0.02","bid":"0.01","ask":"0.02","change":"0","percent_change":"0","volume":"102","open_interest":"123","implied_volatility":"53.13","atm":"0","created_at":"2015-07-28 13:03:07","updated_at":"2015-07-28 13:03:07","moneyness":43.264710650024},{"ticker":"AAPL","type":"put","expiration":"2015-09-17","strike":"75","contract_name":"AAPL150918P00075000","last":"0.04","bid":"0.03","ask":"0.04","change":"0","percent_change":"0","volume":"10","open_interest":"178","implied_volatility":"51.56","atm":"0","created_at":"2015-07-28 13:03:07","updated_at":"2015-07-28 13:03:07","moneyness":39.212189982169},{"ticker":"AAPL","type":"put","expiration":"2015-09-17","strike":"80","contract_name":"AAPL150918P00080000","last":"0.06","bid":"0.05","ask":"0.06","change":"0","percent_change":"0","volume":"21","open_interest":"375","implied_volatility":"48.44","atm":"0","created_at":"2015-07-28 13:03:07","updated_at":"2015-07-28 13:03:07","moneyness":35.159669314314},{"ticker":"AAPL","type":"put","expiration":"2015-09-17","strike":"85","contract_name":"AAPL150918P00085000","last":"0.09","bid":"0.08","ask":"0.09","change":"0","percent_change":"0","volume":"247","open_interest":"1097","implied_volatility":"44.73","atm":"0","created_at":"2015-07-28 13:03:07","updated_at":"2015-07-28 13:03:07","moneyness":31.107148646458},{"ticker":"AAPL","type":"put","expiration":"2015-09-17","strike":"90","contract_name":"AAPL150918P00090000","last":"0.13","bid":"0.11","ask":"0.12","change":"-0.01","percent_change":"-7.14","volume":"18","open_interest":"1945","implied_volatility":"40.23","atm":"0","created_at":"2015-07-28 13:03:07","updated_at":"2015-07-28 13:03:07","moneyness":27.054627978603},{"ticker":"AAPL","type":"put","expiration":"2015-09-17","strike":"95","contract_name":"AAPL150918P00095000","last":"0.16","bid":"0.15","ask":"0.17","change":"-0.03","percent_change":"-15.79","volume":"154","open_interest":"2075","implied_volatility":"36.13","atm":"0","created_at":"2015-07-28 13:03:07","updated_at":"2015-07-28 13:03:07","moneyness":23.002107310747},{"ticker":"AAPL","type":"put","expiration":"2015-09-17","strike":"100","contract_name":"AAPL150918P00100000","last":"0.22","bid":"0.22","ask":"0.23","change":"-0.07","percent_change":"-24.14","volume":"282","open_interest":"2423","implied_volatility":"31.74","atm":"0","created_at":"2015-07-28 13:03:07","updated_at":"2015-07-28 13:03:07","moneyness":18.949586642892},{"ticker":"AAPL","type":"put","expiration":"2015-09-17","strike":"105","contract_name":"AAPL150918P00105000","last":"0.35","bid":"0.33","ask":"0.34","change":"-0.1","percent_change":"-22.22","volume":"79","open_interest":"5081","implied_volatility":"27.71","atm":"0","created_at":"2015-07-28 13:03:07","updated_at":"2015-07-28 13:03:07","moneyness":14.897065975036},{"ticker":"AAPL","type":"put","expiration":"2015-09-17","strike":"110","contract_name":"AAPL150918P00110000","last":"0.61","bid":"0.61","ask":"0.62","change":"-0.19","percent_change":"-23.75","volume":"668","open_interest":"13402","implied_volatility":"24.83","atm":"0","created_at":"2015-07-28 13:03:07","updated_at":"2015-07-28 13:03:07","moneyness":10.844545307181},{"ticker":"AAPL","type":"put","expiration":"2015-09-17","strike":"115","contract_name":"AAPL150918P00115000","last":"1.29","bid":"1.27","ask":"1.29","change":"-0.28","percent_change":"-17.83","volume":"2830","open_interest":"16896","implied_volatility":"23.05","atm":"0","created_at":"2015-07-28 13:03:07","updated_at":"2015-07-28 13:03:07","moneyness":6.7920246393257},{"ticker":"AAPL","type":"put","expiration":"2015-09-17","strike":"120","contract_name":"AAPL150918P00120000","last":"2.7","bid":"2.67","ask":"2.69","change":"-0.38","percent_change":"-12.34","volume":"1322","open_interest":"23043","implied_volatility":"22.16","atm":"0","created_at":"2015-07-28 13:03:07","updated_at":"2015-07-28 13:03:07","moneyness":2.7395039714703},{"ticker":"AAPL","type":"put","expiration":"2015-10-15","strike":"60","contract_name":"AAPL151016P00060000","last":"0.04","bid":"0.01","ask":"0.02","change":"0","percent_change":"0","volume":"2","open_interest":"2642","implied_volatility":"53.91","atm":"0","created_at":"2015-07-28 13:03:07","updated_at":"2015-07-28 13:03:07","moneyness":51.369751985735},{"ticker":"AAPL","type":"put","expiration":"2015-10-15","strike":"65","contract_name":"AAPL151016P00065000","last":"0.03","bid":"0.02","ask":"0.04","change":"0","percent_change":"0","volume":"0","open_interest":"631","implied_volatility":"51.95","atm":"0","created_at":"2015-07-28 13:03:07","updated_at":"2015-07-28 13:03:07","moneyness":47.31723131788},{"ticker":"AAPL","type":"put","expiration":"2015-10-15","strike":"70","contract_name":"AAPL151016P00070000","last":"0.04","bid":"0.04","ask":"0.06","change":"0","percent_change":"0","volume":"0","open_interest":"1587","implied_volatility":"50","atm":"0","created_at":"2015-07-28 13:03:07","updated_at":"2015-07-28 13:03:07","moneyness":43.264710650024},{"ticker":"AAPL","type":"put","expiration":"2015-10-15","strike":"75","contract_name":"AAPL151016P00075000","last":"0.09","bid":"0.06","ask":"0.08","change":"0.01","percent_change":"12.5","volume":"5","open_interest":"1890","implied_volatility":"46.09","atm":"0","created_at":"2015-07-28 13:03:07","updated_at":"2015-07-28 13:03:07","moneyness":39.212189982169},{"ticker":"AAPL","type":"put","expiration":"2015-10-15","strike":"80","contract_name":"AAPL151016P00080000","last":"0.11","bid":"0.1","ask":"0.11","change":"0","percent_change":"0","volume":"279","open_interest":"3085","implied_volatility":"42.58","atm":"0","created_at":"2015-07-28 13:03:07","updated_at":"2015-07-28 13:03:07","moneyness":35.159669314314},{"ticker":"AAPL","type":"put","expiration":"2015-10-15","strike":"85","contract_name":"AAPL151016P00085000","last":"0.1","bid":"0.14","ask":"0.15","change":"0","percent_change":"0","volume":"4","open_interest":"3125","implied_volatility":"38.97","atm":"0","created_at":"2015-07-28 13:03:07","updated_at":"2015-07-28 13:03:07","moneyness":31.107148646458},{"ticker":"AAPL","type":"put","expiration":"2015-10-15","strike":"90","contract_name":"AAPL151016P00090000","last":"0.21","bid":"0.19","ask":"0.2","change":"0.03","percent_change":"16.67","volume":"20","open_interest":"6432","implied_volatility":"35.35","atm":"0","created_at":"2015-07-28 13:03:07","updated_at":"2015-07-28 13:03:07","moneyness":27.054627978603},{"ticker":"AAPL","type":"put","expiration":"2015-10-15","strike":"95","contract_name":"AAPL151016P00095000","last":"0.32","bid":"0.27","ask":"0.28","change":"0","percent_change":"0","volume":"57","open_interest":"8184","implied_volatility":"31.98","atm":"0","created_at":"2015-07-28 13:03:07","updated_at":"2015-07-28 13:03:07","moneyness":23.002107310747},{"ticker":"AAPL","type":"put","expiration":"2015-10-15","strike":"100","contract_name":"AAPL151016P00100000","last":"0.41","bid":"0.4","ask":"0.41","change":"-0.08","percent_change":"-16.33","volume":"3","open_interest":"24028","implied_volatility":"28.91","atm":"0","created_at":"2015-07-28 13:03:07","updated_at":"2015-07-28 13:03:07","moneyness":18.949586642892},{"ticker":"AAPL","type":"put","expiration":"2015-10-15","strike":"105","contract_name":"AAPL151016P00105000","last":"0.65","bid":"0.64","ask":"0.65","change":"-0.15","percent_change":"-18.75","volume":"195","open_interest":"13382","implied_volatility":"26.27","atm":"0","created_at":"2015-07-28 13:03:07","updated_at":"2015-07-28 13:03:07","moneyness":14.897065975036},{"ticker":"AAPL","type":"put","expiration":"2015-10-15","strike":"110","contract_name":"AAPL151016P00110000","last":"1.14","bid":"1.14","ask":"1.16","change":"-0.25","percent_change":"-17.99","volume":"208","open_interest":"18260","implied_volatility":"24.52","atm":"0","created_at":"2015-07-28 13:03:08","updated_at":"2015-07-28 13:03:08","moneyness":10.844545307181},{"ticker":"AAPL","type":"put","expiration":"2015-10-15","strike":"115","contract_name":"AAPL151016P00115000","last":"2.11","bid":"2.07","ask":"2.09","change":"-0.29","percent_change":"-12.08","volume":"332","open_interest":"33302","implied_volatility":"23.23","atm":"0","created_at":"2015-07-28 13:03:08","updated_at":"2015-07-28 13:03:08","moneyness":6.7920246393257},{"ticker":"AAPL","type":"put","expiration":"2015-10-15","strike":"120","contract_name":"AAPL151016P00120000","last":"3.7","bid":"3.65","ask":"3.75","change":"-0.45","percent_change":"-10.84","volume":"258","open_interest":"27381","implied_volatility":"22.75","atm":"0","created_at":"2015-07-28 13:03:08","updated_at":"2015-07-28 13:03:08","moneyness":2.7395039714703},{"ticker":"AAPL","type":"put","expiration":"2015-11-19","strike":"95","contract_name":"AAPL151120P00095000","last":"0.65","bid":"0.56","ask":"0.59","change":"0","percent_change":"0","volume":"94","open_interest":"15261","implied_volatility":"31.28","atm":"0","created_at":"2015-07-28 13:03:08","updated_at":"2015-07-28 13:03:08","moneyness":23.002107310747},{"ticker":"AAPL","type":"put","expiration":"2015-11-19","strike":"100","contract_name":"AAPL151120P00100000","last":"0.97","bid":"0.86","ask":"0.91","change":"-0.01","percent_change":"-1.02","volume":"7","open_interest":"1043","implied_volatility":"29.4","atm":"0","created_at":"2015-07-28 13:03:08","updated_at":"2015-07-28 13:03:08","moneyness":18.949586642892},{"ticker":"AAPL","type":"put","expiration":"2015-11-19","strike":"105","contract_name":"AAPL151120P00105000","last":"1.48","bid":"1.36","ask":"1.43","change":"-0.14","percent_change":"-8.64","volume":"30","open_interest":"2260","implied_volatility":"27.82","atm":"0","created_at":"2015-07-28 13:03:08","updated_at":"2015-07-28 13:03:08","moneyness":14.897065975036},{"ticker":"AAPL","type":"put","expiration":"2015-11-19","strike":"110","contract_name":"AAPL151120P00110000","last":"2.42","bid":"2.23","ask":"2.29","change":"-0.13","percent_change":"-5.1","volume":"32","open_interest":"2844","implied_volatility":"26.73","atm":"0","created_at":"2015-07-28 13:03:08","updated_at":"2015-07-28 13:03:08","moneyness":10.844545307181},{"ticker":"AAPL","type":"put","expiration":"2015-11-19","strike":"115","contract_name":"AAPL151120P00115000","last":"3.75","bid":"3.55","ask":"3.65","change":"-0.15","percent_change":"-3.85","volume":"27","open_interest":"3948","implied_volatility":"26.17","atm":"0","created_at":"2015-07-28 13:03:08","updated_at":"2015-07-28 13:03:08","moneyness":6.7920246393257},{"ticker":"AAPL","type":"put","expiration":"2015-11-19","strike":"120","contract_name":"AAPL151120P00120000","last":"5.5","bid":"5.45","ask":"5.55","change":"-0.5","percent_change":"-8.33","volume":"152","open_interest":"2444","implied_volatility":"25.75","atm":"0","created_at":"2015-07-28 13:03:08","updated_at":"2015-07-28 13:03:08","moneyness":2.7395039714703},{"ticker":"AAPL","type":"put","expiration":"2015-12-17","strike":"70","contract_name":"AAPL151218P00070000","last":"0.15","bid":"0.11","ask":"0.17","change":"0","percent_change":"0","volume":"30","open_interest":"403","implied_volatility":"43.26","atm":"0","created_at":"2015-07-28 13:03:08","updated_at":"2015-07-28 13:03:08","moneyness":43.264710650024},{"ticker":"AAPL","type":"put","expiration":"2015-12-17","strike":"75","contract_name":"AAPL151218P00075000","last":"0.16","bid":"0.16","ask":"0.22","change":"0","percent_change":"0","volume":"0","open_interest":"124","implied_volatility":"40.09","atm":"0","created_at":"2015-07-28 13:03:08","updated_at":"2015-07-28 13:03:08","moneyness":39.212189982169},{"ticker":"AAPL","type":"put","expiration":"2015-12-17","strike":"80","contract_name":"AAPL151218P00080000","last":"0.27","bid":"0.24","ask":"0.29","change":"0","percent_change":"0","volume":"41","open_interest":"1361","implied_volatility":"37.16","atm":"0","created_at":"2015-07-28 13:03:08","updated_at":"2015-07-28 13:03:08","moneyness":35.159669314314},{"ticker":"AAPL","type":"put","expiration":"2015-12-17","strike":"85","contract_name":"AAPL151218P00085000","last":"0.34","bid":"0.34","ask":"0.38","change":"0","percent_change":"0","volume":"6","open_interest":"422","implied_volatility":"34.3","atm":"0","created_at":"2015-07-28 13:03:08","updated_at":"2015-07-28 13:03:08","moneyness":31.107148646458},{"ticker":"AAPL","type":"put","expiration":"2015-12-17","strike":"90","contract_name":"AAPL151218P00090000","last":"0.51","bid":"0.47","ask":"0.53","change":"0","percent_change":"0","volume":"6","open_interest":"1064","implied_volatility":"31.93","atm":"0","created_at":"2015-07-28 13:03:08","updated_at":"2015-07-28 13:03:08","moneyness":27.054627978603},{"ticker":"AAPL","type":"put","expiration":"2015-12-17","strike":"95","contract_name":"AAPL151218P00095000","last":"0.71","bid":"0.72","ask":"0.76","change":"0","percent_change":"0","volume":"100","open_interest":"1400","implied_volatility":"29.81","atm":"0","created_at":"2015-07-28 13:03:08","updated_at":"2015-07-28 13:03:08","moneyness":23.002107310747},{"ticker":"AAPL","type":"put","expiration":"2015-12-17","strike":"100","contract_name":"AAPL151218P00100000","last":"1.25","bid":"1.1","ask":"1.16","change":"-0.01","percent_change":"-0.79","volume":"56","open_interest":"1739","implied_volatility":"28.27","atm":"0","created_at":"2015-07-28 13:03:08","updated_at":"2015-07-28 13:03:08","moneyness":18.949586642892},{"ticker":"AAPL","type":"put","expiration":"2015-12-17","strike":"105","contract_name":"AAPL151218P00105000","last":"1.75","bid":"1.72","ask":"1.79","change":"-0.18","percent_change":"-9.33","volume":"56","open_interest":"2585","implied_volatility":"27.01","atm":"0","created_at":"2015-07-28 13:03:08","updated_at":"2015-07-28 13:03:08","moneyness":14.897065975036},{"ticker":"AAPL","type":"put","expiration":"2015-12-17","strike":"110","contract_name":"AAPL151218P00110000","last":"2.9","bid":"2.68","ask":"2.74","change":"-0.02","percent_change":"-0.68","volume":"19","open_interest":"6267","implied_volatility":"26","atm":"0","created_at":"2015-07-28 13:03:08","updated_at":"2015-07-28 13:03:08","moneyness":10.844545307181},{"ticker":"AAPL","type":"put","expiration":"2015-12-17","strike":"115","contract_name":"AAPL151218P00115000","last":"4.16","bid":"4.05","ask":"4.2","change":"-0.29","percent_change":"-6.52","volume":"218","open_interest":"14319","implied_volatility":"25.53","atm":"0","created_at":"2015-07-28 13:03:08","updated_at":"2015-07-28 13:03:08","moneyness":6.7920246393257},{"ticker":"AAPL","type":"put","expiration":"2015-12-17","strike":"120","contract_name":"AAPL151218P00120000","last":"6","bid":"6","ask":"6.15","change":"-0.5","percent_change":"-7.69","volume":"357","open_interest":"19577","implied_volatility":"25.12","atm":"0","created_at":"2015-07-28 13:03:08","updated_at":"2015-07-28 13:03:08","moneyness":2.7395039714703},{"ticker":"AAPL","type":"put","expiration":"2016-04-14","strike":"75","contract_name":"AAPL160415P00075000","last":"0.39","bid":"0.38","ask":"0.44","change":"0","percent_change":"0","volume":"0","open_interest":"249","implied_volatility":"33.45","atm":"0","created_at":"2015-07-28 13:03:08","updated_at":"2015-07-28 13:03:08","moneyness":39.212189982169},{"ticker":"AAPL","type":"put","expiration":"2016-04-14","strike":"80","contract_name":"AAPL160415P00080000","last":"0.57","bid":"0.57","ask":"0.64","change":"0","percent_change":"0","volume":"3","open_interest":"1883","implied_volatility":"32.03","atm":"0","created_at":"2015-07-28 13:03:08","updated_at":"2015-07-28 13:03:08","moneyness":35.159669314314},{"ticker":"AAPL","type":"put","expiration":"2016-04-14","strike":"85","contract_name":"AAPL160415P00085000","last":"0.9","bid":"0.81","ask":"0.9","change":"0","percent_change":"0","volume":"17","open_interest":"357","implied_volatility":"30.53","atm":"0","created_at":"2015-07-28 13:03:08","updated_at":"2015-07-28 13:03:08","moneyness":31.107148646458},{"ticker":"AAPL","type":"put","expiration":"2016-04-14","strike":"90","contract_name":"AAPL160415P00090000","last":"1.31","bid":"1.18","ask":"1.27","change":"0","percent_change":"0","volume":"1","open_interest":"619","implied_volatility":"29.21","atm":"0","created_at":"2015-07-28 13:03:08","updated_at":"2015-07-28 13:03:08","moneyness":27.054627978603},{"ticker":"AAPL","type":"put","expiration":"2016-04-14","strike":"95","contract_name":"AAPL160415P00095000","last":"1.81","bid":"1.71","ask":"1.8","change":"0","percent_change":"0","volume":"95","open_interest":"534","implied_volatility":"28.11","atm":"0","created_at":"2015-07-28 13:03:08","updated_at":"2015-07-28 13:03:08","moneyness":23.002107310747},{"ticker":"AAPL","type":"put","expiration":"2016-04-14","strike":"100","contract_name":"AAPL160415P00100000","last":"2.48","bid":"2.46","ask":"2.54","change":"-0.18","percent_change":"-6.77","volume":"2","open_interest":"1085","implied_volatility":"27.18","atm":"0","created_at":"2015-07-28 13:03:08","updated_at":"2015-07-28 13:03:08","moneyness":18.949586642892},{"ticker":"AAPL","type":"put","expiration":"2016-04-14","strike":"105","contract_name":"AAPL160415P00105000","last":"3.7","bid":"3.5","ask":"3.6","change":"0","percent_change":"0","volume":"33","open_interest":"618","implied_volatility":"26.58","atm":"0","created_at":"2015-07-28 13:03:08","updated_at":"2015-07-28 13:03:08","moneyness":14.897065975036},{"ticker":"AAPL","type":"put","expiration":"2016-04-14","strike":"110","contract_name":"AAPL160415P00110000","last":"4.95","bid":"4.85","ask":"5","change":"-0.29","percent_change":"-5.53","volume":"25","open_interest":"1828","implied_volatility":"26.12","atm":"0","created_at":"2015-07-28 13:03:08","updated_at":"2015-07-28 13:03:08","moneyness":10.844545307181},{"ticker":"AAPL","type":"put","expiration":"2016-04-14","strike":"115","contract_name":"AAPL160415P00115000","last":"6.98","bid":"6.65","ask":"6.7","change":"0","percent_change":"0","volume":"187","open_interest":"7007","implied_volatility":"25.56","atm":"0","created_at":"2015-07-28 13:03:08","updated_at":"2015-07-28 13:03:08","moneyness":6.7920246393257},{"ticker":"AAPL","type":"put","expiration":"2016-04-14","strike":"120","contract_name":"AAPL160415P00120000","last":"9","bid":"8.8","ask":"8.9","change":"-0.17","percent_change":"-1.85","volume":"15","open_interest":"4446","implied_volatility":"25.37","atm":"0","created_at":"2015-07-28 13:03:08","updated_at":"2015-07-28 13:03:08","moneyness":2.7395039714703}]
